sop/__init__.py
sop/btree.py
sop/call_go.py
sop/cassandra.py
sop/context.py
sop/database.py
sop/demo.py
sop/httpserver.py
sop/libjsondb_arm64linux.so
sop/logger.py
sop/redis.py
sop/search.py
sop/test_btree.py
sop/test_btree_idx.py
sop/test_btree_noredis.py
sop/test_logging.py
sop/transaction.py
sop/ai/README.md
sop/ai/__init__.py
sop/ai/database.py
sop/ai/langchain.py
sop/ai/model.py
sop/ai/test_btree.py
sop/ai/test_langchain.py
sop/ai/vector.py
sop/examples/README.md
sop/examples/__init__.py
sop/examples/backend_comparison.py
sop/examples/cassandra_demo.py
sop/examples/complex_key_demo.py
sop/examples/complex_key_dict_lookup.py
sop/examples/concurrent_demo.py
sop/examples/concurrent_demo_standalone.py
sop/examples/erasure_coding_config_demo.py
sop/examples/full_replication_config_demo.py
sop/examples/langchain_demo.py
sop/examples/large_complex_demo.py
sop/examples/large_complex_key_demo.py
sop/examples/large_simple_demo.py
sop/examples/logging_demo.py
sop/examples/metadata_key_demo.py
sop/examples/modelstore_demo.py
sop/examples/multi_tenant_cassandra.py
sop/examples/multi_tenant_redis_url.py
sop/examples/test_cassandra_init.py
sop/examples/test_clustered_noredis.py
sop/examples/test_redis_init.py
sop/examples/unified_demo.py
sop/examples/vector_clustered_demo.py
sop/examples/vector_clustered_replication_demo.py
sop/examples/vector_demo.py
sop/examples/vector_replication_demo.py
sop4py-2.0.44.dist-info/METADATA
sop4py-2.0.44.dist-info/WHEEL
sop4py-2.0.44.dist-info/entry_points.txt
sop4py-2.0.44.dist-info/top_level.txt
sop4py-2.0.44.dist-info/RECORD
