Metadata-Version: 2.1
Name: sop4py
Version: 2.0.44
Summary: Scalable Objects Persistence (SOP) V2 for Python. General Public Availability (GPA) Release
Home-page: https://pypi.org/project/sop-python-beta-3
Author: Gerardo Recinto
Author-email: gerardorecinto@yahoo.com
License: UNKNOWN
Platform: UNKNOWN
Classifier: Programming Language :: Python :: 3
Classifier: License :: OSI Approved :: MIT License
Classifier: Operating System :: OS Independent
Requires-Python: >=3.7
